rubiks/__init__.py
rubiks-0.0.1.dist-info/LICENSE
rubiks-0.0.1.dist-info/METADATA
rubiks-0.0.1.dist-info/WHEEL
rubiks-0.0.1.dist-info/top_level.txt
rubiks-0.0.1.dist-info/RECORD
